Metadata-Version: 2.1
Name: Beads
Version: 0.1.4
Summary: A commandline tool to parse fine state machines into code.
Home-page: https://gitlab.com/a.wuillemet/beads
Author: Jakob Baatz, Rico Possienka, Pavel Nepke, Marco Wenning, Adrian Wuillemet
License: UNKNOWN
Keywords: state machine code generation gui
Platform: UNKNOWN
Classifier: Programming Language :: Python :: 3
Classifier: License :: OSI Approved :: MIT License
Classifier: Operating System :: OS Independent
Requires-Dist: click
Requires-Dist: eel
Requires-Dist: markdown
